var Villa = {
    "type": "FeatureCollection",
    "crs": { "type": "name", "properties": { "name": "urn:ogc:def:crs:OGC:1.3:CRS84" } },
    "features": [
    { "type": "Feature", "properties": { "id": 3, "descrip": "Villa" }, "geometry": { "type": "Point", "coordinates": [ -64.78398, 18.32488 ] } }
    ]
    }